caseutil/__init__.py
caseutil/__main__.py
caseutil/__version__.py
caseutil/py.typed
caseutil-0.7.1.dist-info/METADATA
caseutil-0.7.1.dist-info/WHEEL
caseutil-0.7.1.dist-info/entry_points.txt
caseutil-0.7.1.dist-info/licenses/LICENSE
caseutil-0.7.1.dist-info/RECORD
