Metadata-Version: 2.4
Name: caseutil
Version: 0.7.1
Summary: Case convert and verify for Python: snake_case, camelCase, kebab-case, and more.
Project-URL: Documentation, https://caseutil.readthedocs.io
Project-URL: Repository, https://github.com/makukha/caseutil
Project-URL: Issues, https://github.com/makukha/caseutil/issues
Project-URL: Changelog, https://github.com/makukha/caseutil/releases
Author-email: Michael Makukha <m.makukha@gmail.com>
License: MIT
License-File: LICENSE
Keywords: camel case,case,case converter,convert,kebab case,pascal case,screaming snake case,snake case,string case,text case,text case converter
Classifier: Development Status :: 4 - Beta
Classifier: Environment :: Console
Classifier: Intended Audience :: Developers
Classifier: License :: OSI Approved :: MIT License
Classifier: Operating System :: OS Independent
Classifier: Programming Language :: Python
Classifier: Programming Language :: Python :: 2
Classifier: Programming Language :: Python :: 2.7
Classifier: Programming Language :: Python :: 3
Classifier: Programming Language :: Python :: 3.5
Classifier: Programming Language :: Python :: 3.6
Classifier: Programming Language :: Python :: 3.7
Classifier: Programming Language :: Python :: 3.8
Classifier: Programming Language :: Python :: 3.9
Classifier: Programming Language :: Python :: 3.10
Classifier: Programming Language :: Python :: 3.11
Classifier: Programming Language :: Python :: 3.12
Classifier: Programming Language :: Python :: 3.13
Classifier: Programming Language :: Python :: 3.14
Classifier: Programming Language :: Python :: Implementation :: CPython
Classifier: Programming Language :: Python :: Implementation :: PyPy
Classifier: Topic :: Software Development
Classifier: Topic :: Text Processing
Classifier: Topic :: Utilities
Classifier: Typing :: Typed
Requires-Python: !=3.0,!=3.1,!=3.2,!=3.3,!=3.4,>=2.7
